bktree/__init__.py
bktree/bktree.py
bktree/test.py
bktree-0.1.2.dist-info/DESCRIPTION.rst
bktree-0.1.2.dist-info/METADATA
bktree-0.1.2.dist-info/RECORD
bktree-0.1.2.dist-info/WHEEL
bktree-0.1.2.dist-info/metadata.json
bktree-0.1.2.dist-info/top_level.txt
