Metadata-Version: 2.0
Name: bktree
Version: 0.1.2
Summary: A pure-Python implementation of BK-trees
Home-page: https://github.com/ryanfox/bktree
Author: Ryan Fox
Author-email: ryan@foxrow.com
License: MIT
Download-URL: https://github.com/ryanfox/bktree/tarball/0.1
Keywords: bktree,bk tree,data structures
Platform: UNKNOWN
